brain_games/__init__.py
brain_games/cli.py
brain_games/constants.py
brain_games/game_logic.py
brain_games/scripts/__init__.py
brain_games/scripts/brain_calc.py
brain_games/scripts/brain_even.py
brain_games/scripts/brain_games.py
brain_games/scripts/brain_gcd.py
brain_games/scripts/brain_prime.py
brain_games/scripts/brain_progression.py
2rage_brain_games-1.0.2.dist-info/METADATA
2rage_brain_games-1.0.2.dist-info/WHEEL
2rage_brain_games-1.0.2.dist-info/entry_points.txt
2rage_brain_games-1.0.2.dist-info/RECORD
