Metadata-Version: 2.1
Name: 2rage-brain-games
Version: 1.0.2
Summary: 2rage-brain-games is a set of console-based brain games built in Python. Each game provides a different mental challenge, ranging from calculations and number theory to recognition of even numbers. The project includes games like 'brain-even', 'brain-calc', 'brain-gcd', 'brain-progression', and 'brain-prime'. Test your mental agility and have fun with this collection of games!
Author: 2rage
Author-email: the2rage@icloud.com
Requires-Python: >=3.12,<4.0
Classifier: Programming Language :: Python :: 3
Classifier: Programming Language :: Python :: 3.12
Requires-Dist: colorama (>=0.4.6,<0.5.0)
Requires-Dist: prompt (>=0.4.1,<0.5.0)
